{
	"info": {
		"_postman_id": "ccf17430-e835-40c3-889d-a9701fa83339",
		"name": "XCode",
		"schema": "https://schema.getpostman.com/json/collection/v2.1.0/collection.json",
		"_exporter_id": "45426403"
	},
	"item": [
		{
			"name": "CreateUser",
			"request": {
				"method": "POST",
				"header": [],
				"body": {
					"mode": "raw",
					"raw": "// {\n//     \"name\": \"Morpheus\"\n// }\n\n{\n    \"id\": 10,\n    \"name\": \"Morpheus\"\n}",
					"options": {
						"raw": {
							"language": "json"
						}
					}
				},
				"url": {
					"raw": "http://localhost:8081/users",
					"protocol": "http",
					"host": [
						"localhost"
					],
					"port": "8081",
					"path": [
						"users"
					]
				}
			},
			"response": []
		}
	]
}